wimby_sf/__init__.py
wimby_sf/wimby_sf_functions.py
wimby_sf-2.0.0.dist-info/METADATA
wimby_sf-2.0.0.dist-info/WHEEL
wimby_sf-2.0.0.dist-info/top_level.txt
wimby_sf-2.0.0.dist-info/RECORD
